farmtool/__init__.py
farmtool/cows_api.py
farmtool/database_cows_functions.py
farmtool/main.py
farmtool/models.py
farmtool-1.0.1.dist-info/entry_points.txt
farmtool-1.0.1.dist-info/METADATA
farmtool-1.0.1.dist-info/WHEEL
farmtool-1.0.1.dist-info/RECORD
