Metadata-Version: 2.1
Name: farmtool
Version: 1.0.1
Summary: Farmtool to help the farmer to automate and handle Cowsheds.
Author: Bishara
Requires-Python: >=3.10,<4.0
Classifier: Programming Language :: Python :: 3
Classifier: Programming Language :: Python :: 3.10
Classifier: Programming Language :: Python :: 3.11
Classifier: Programming Language :: Python :: 3.12
Requires-Dist: certifi (>=2023.11.17,<2024.0.0)
Requires-Dist: cron-validator (>=1.0.8,<2.0.0)
Requires-Dist: datetime (>=5.3,<6.0)
Requires-Dist: fastapi (>=0.104.1,<0.105.0)
Requires-Dist: httpx (>=0.25.2,<0.26.0)
Requires-Dist: motor (>=3.3.2,<4.0.0)
Requires-Dist: requests (>=2.31.0,<3.0.0)
Requires-Dist: unitest (>=1.4.34,<2.0.0)
Requires-Dist: uvicorn (>=0.24.0.post1,<0.25.0)
